<?xml version="1.1" encoding="UTF-8"?>

<channel name="xfce4-panel" version="1.0">
  <property name="configver" type="int" value="2"/>
  <property name="panels" type="array">
    <value type="int" value="1"/>
    <property name="dark-mode" type="bool" value="true"/>
    <property name="panel-1" type="empty">
      <property name="position" type="string" value="p=8;x=960;y=1066"/>
      <property name="length" type="double" value="100"/>
      <property name="position-locked" type="bool" value="true"/>
      <property name="icon-size" type="uint" value="0"/>
      <property name="size" type="uint" value="50"/>
      <property name="plugin-ids" type="array">
        <value type="int" value="7"/>
        <value type="int" value="2"/>
        <value type="int" value="3"/>
        <value type="int" value="15"/>
        <value type="int" value="5"/>
        <value type="int" value="6"/>
        <value type="int" value="11"/>
        <value type="int" value="13"/>
        <value type="int" value="20"/>
        <value type="int" value="12"/>
        <value type="int" value="29"/>
        <value type="int" value="25"/>
        <value type="int" value="1"/>
        <value type="int" value="8"/>
        <value type="int" value="10"/>
        <value type="int" value="9"/>
        <value type="int" value="23"/>
        <value type="int" value="14"/>
        <value type="int" value="30"/>
      </property>
      <property name="background-style" type="uint" value="2"/>
      <property name="background-rgba" type="array">
        <value type="double" value="0.039216000000000001"/>
        <value type="double" value="0.043137000000000002"/>
        <value type="double" value="0.066667000000000004"/>
        <value type="double" value="1"/>
      </property>
      <property name="background-image" type="string" value="/usr/share/themes/blackarch-xfce/xfwm4/panel.png"/>
      <property name="enable-struts" type="bool" value="true"/>
      <property name="nrows" type="uint" value="1"/>
      <property name="border-width" type="uint" value="1"/>
    </property>
  </property>
  <property name="plugins" type="empty">
    <property name="plugin-2" type="string" value="tasklist">
      <property name="grouping" type="uint" value="1"/>
    </property>
    <property name="plugin-3" type="string" value="separator">
      <property name="expand" type="bool" value="true"/>
      <property name="style" type="uint" value="0"/>
    </property>
    <property name="plugin-5" type="string" value="separator">
      <property name="style" type="uint" value="0"/>
    </property>
    <property name="plugin-6" type="string" value="systray">
      <property name="square-icons" type="bool" value="true"/>
      <property name="known-items" type="array">
        <value type="string" value="Thunderbird"/>
        <value type="string" value="proton-vpn-app"/>
        <value type="string" value="TelegramDesktop"/>
      </property>
      <property name="known-legacy-items" type="array">
        <value type="string" value="parole"/>
        <value type="string" value="vmware-tray"/>
        <value type="string" value="xfce4-power-manager"/>
      </property>
    </property>
    <property name="plugin-8" type="string" value="pulseaudio">
      <property name="enable-keyboard-shortcuts" type="bool" value="true"/>
      <property name="show-notifications" type="bool" value="true"/>
      <property name="known-players" type="string" value="Chromium;firefox;org.telegram.desktop;parole"/>
    </property>
    <property name="plugin-9" type="string" value="power-manager-plugin"/>
    <property name="plugin-10" type="string" value="notification-plugin"/>
    <property name="plugin-11" type="string" value="separator">
      <property name="style" type="uint" value="0"/>
    </property>
    <property name="plugin-12" type="string" value="clock">
      <property name="mode" type="uint" value="4"/>
      <property name="show-seconds" type="bool" value="true"/>
      <property name="flash-separators" type="bool" value="false"/>
      <property name="show-inactive" type="bool" value="false"/>
      <property name="show-week-numbers" type="bool" value="true"/>
      <property name="timezone" type="string" value="Asia/Tashkent"/>
      <property name="digital-date-font" type="string" value="Sans 10"/>
      <property name="digital-time-font" type="string" value="Sans 11"/>
    </property>
    <property name="plugin-13" type="string" value="separator">
      <property name="style" type="uint" value="0"/>
    </property>
    <property name="plugin-14" type="string" value="actions">
      <property name="button-title" type="uint" value="3"/>
      <property name="ask-confirmation" type="bool" value="false"/>
      <property name="custom-title" type="string" value="User"/>
      <property name="appearance" type="uint" value="0"/>
      <property name="items" type="array">
        <value type="string" value="-lock-screen"/>
        <value type="string" value="-switch-user"/>
        <value type="string" value="-separator"/>
        <value type="string" value="-suspend"/>
        <value type="string" value="-hibernate"/>
        <value type="string" value="-hybrid-sleep"/>
        <value type="string" value="-separator"/>
        <value type="string" value="-shutdown"/>
        <value type="string" value="-restart"/>
        <value type="string" value="-separator"/>
        <value type="string" value="+logout"/>
        <value type="string" value="-logout-dialog"/>
      </property>
    </property>
    <property name="plugin-7" type="string" value="whiskermenu">
      <property name="button-title" type="string" value="  Menu  "/>
      <property name="button-icon" type="string" value="distributor-logo-blackarch"/>
      <property name="show-button-title" type="bool" value="true"/>
      <property name="view-mode" type="int" value="2"/>
      <property name="sort-categories" type="bool" value="false"/>
      <property name="favorites-in-recent" type="bool" value="true"/>
      <property name="position-search-alternate" type="bool" value="true"/>
      <property name="position-commands-alternate" type="bool" value="true"/>
      <property name="position-categories-alternate" type="bool" value="true"/>
      <property name="command-switchuser" type="string" value="gdmflexiserver"/>
      <property name="favorites" type="array">
        <value type="string" value="firefox.desktop"/>
        <value type="string" value="xfce4-file-manager.desktop"/>
        <value type="string" value="xfce4-terminal-emulator.desktop"/>
      </property>
      <property name="category-icon-size" type="int" value="2"/>
      <property name="menu-width" type="int" value="800"/>
      <property name="menu-height" type="int" value="650"/>
      <property name="show-command-logout" type="bool" value="true"/>
      <property name="launcher-icon-size" type="int" value="3"/>
      <property name="menu-opacity" type="int" value="96"/>
      <property name="profile-shape" type="int" value="1"/>
      <property name="show-button-icon" type="bool" value="true"/>
      <property name="default-category" type="int" value="0"/>
      <property name="recent" type="array">
        <value type="string" value="xfce4-file-manager.desktop"/>
      </property>
    </property>
    <property name="plugin-1" type="string" value="xfce4-clipman-plugin"/>
    <property name="clipman" type="empty">
      <property name="settings" type="empty">
        <property name="show-qr-code" type="bool" value="false"/>
        <property name="add-primary-clipboard" type="bool" value="false"/>
        <property name="max-texts-in-history" type="uint" value="1000"/>
        <property name="enable-actions" type="bool" value="false"/>
        <property name="save-on-quit" type="bool" value="true"/>
        <property name="persistent-primary-clipboard" type="bool" value="true"/>
      </property>
      <property name="tweaks" type="empty">
        <property name="max-menu-items" type="uint" value="100"/>
        <property name="paste-on-activate" type="uint" value="2"/>
        <property name="reverse-menu-order" type="bool" value="false"/>
      </property>
    </property>
    <property name="plugin-15" type="string" value="cpufreq"/>
    <property name="plugin-20" type="string" value="netload"/>
    <property name="plugin-23" type="string" value="xfce4-time-out-plugin"/>
    <property name="plugin-25" type="string" value="xfce4-timer-plugin"/>
    <property name="plugin-29" type="string" value="separator">
      <property name="style" type="uint" value="0"/>
      <property name="expand" type="bool" value="false"/>
    </property>
    <property name="plugin-30" type="string" value="wavelan"/>
  </property>
</channel>
